npm_registry_time_machine/__init__.py
npm_registry_time_machine/__main__.py
npm_registry_time_machine-1.0.11.dist-info/LICENSE
npm_registry_time_machine-1.0.11.dist-info/METADATA
npm_registry_time_machine-1.0.11.dist-info/WHEEL
npm_registry_time_machine-1.0.11.dist-info/entry_points.txt
npm_registry_time_machine-1.0.11.dist-info/top_level.txt
npm_registry_time_machine-1.0.11.dist-info/RECORD
