Metadata-Version: 2.1
Name: npm-registry-time-machine
Version: 1.0.11
Summary: Proxy for limiting the release dates of packages
Author-email: Alexandr Gusev <alphacity@yandex.ru>
License: MIT
Project-URL: Homepage, https://github.com/Alexandr-Gusev/npm-registry-time-machine
Keywords: npm,registry,time-machine
Classifier: Programming Language :: Python :: 3
Classifier: License :: OSI Approved :: MIT License
Classifier: Operating System :: OS Independent
Requires-Python: >=3.9.9
License-File: LICENSE
Requires-Dist: aiohttp>=3.8.5
Requires-Dist: aiohttp_requests>=0.2.2
